memory/__init__.py
memory/brain.py
memory/compression.py
memory/embeddings.py
memory/log_util.py
memory/resources/en_stopwords.pkl
memory/resources/lid.176.ftz
memory/resources/pt_stopwords.pkl
tests/__init__.py
tests/test_embedding_extraction.py
tests/test_logger.py
tests/test_memory.py
chatmemorydb-1.3.dist-info/LICENSE
chatmemorydb-1.3.dist-info/METADATA
chatmemorydb-1.3.dist-info/WHEEL
chatmemorydb-1.3.dist-info/top_level.txt
chatmemorydb-1.3.dist-info/RECORD
