Metadata-Version: 2.1
Name: chatmemorydb
Version: 1.3
Author: Carlo Moro
Author-email: Carlo Moro <cnmoro@gmail.com>
Project-URL: Homepage, https://github.com/cnmoro/ChatMemory
Project-URL: Bug Tracker, https://github.com/cnmoro/ChatMemory/issues
Classifier: Programming Language :: Python :: 3
Classifier: License :: OSI Approved :: MIT License
Classifier: Operating System :: OS Independent
Requires-Python: >=3.7
License-File: LICENSE
Requires-Dist: minivectordb >=2.2.1
Requires-Dist: logzero
Requires-Dist: numpy <2
Requires-Dist: nltk
Requires-Dist: scikit-learn
Requires-Dist: tiktoken
Requires-Dist: fasttext
